element_array_ephys/__init__.py
element_array_ephys/ephys_acute.py
element_array_ephys/ephys_chronic.py
element_array_ephys/ephys_no_curation.py
element_array_ephys/ephys_precluster.py
element_array_ephys/ephys_report.py
element_array_ephys/probe.py
element_array_ephys/version.py
element_array_ephys/export/__init__.py
element_array_ephys/export/nwb/__init__.py
element_array_ephys/export/nwb/nwb.py
element_array_ephys/plotting/__init__.py
element_array_ephys/plotting/corr.py
element_array_ephys/plotting/probe_level.py
element_array_ephys/plotting/qc.py
element_array_ephys/plotting/unit_level.py
element_array_ephys/plotting/widget.py
element_array_ephys/readers/__init__.py
element_array_ephys/readers/kilosort.py
element_array_ephys/readers/kilosort_triggering.py
element_array_ephys/readers/openephys.py
element_array_ephys/readers/spikeglx.py
element_array_ephys/readers/utils.py
element_array_ephys-0.2.11.dist-info/LICENSE
element_array_ephys-0.2.11.dist-info/METADATA
element_array_ephys-0.2.11.dist-info/WHEEL
element_array_ephys-0.2.11.dist-info/top_level.txt
element_array_ephys-0.2.11.dist-info/RECORD
